<annotation>
	<folder>tlavisse</folder>
	<filename>gralljea_pos_002.jpg</filename>
	<path>gralljea_pos_002.jpg</path>
	<source>
		<database>Unknown</database>
	</source>
	<size>
		<width>863</width>
		<height>1150</height>
		<depth>3</depth>
	</size>
	<segmented>0</segmented>
	<object>
		<name>ecocup</name>
		<pose>Unspecified</pose>
		<truncated>0</truncated>
		<difficult>0</difficult>
		<bndbox>
			<xmin>631</xmin>
			<ymin>661</ymin>
			<xmax>717</xmax>
			<ymax>813</ymax>
		</bndbox>
	</object>
	<object>
		<name>ecocup</name>
		<pose>Unspecified</pose>
		<truncated>0</truncated>
		<difficult>0</difficult>
		<bndbox>
			<xmin>277</xmin>
			<ymin>644</ymin>
			<xmax>403</xmax>
			<ymax>756</ymax>
		</bndbox>
	</object>
	<object>
		<name>ecocup</name>
		<pose>Unspecified</pose>
		<truncated>0</truncated>
		<difficult>1</difficult>
		<bndbox>
			<xmin>330</xmin>
			<ymin>576</ymin>
			<xmax>400</xmax>
			<ymax>701</ymax>
		</bndbox>
	</object>
	<object>
		<name>ecocup</name>
		<pose>Unspecified</pose>
		<truncated>0</truncated>
		<difficult>0</difficult>
		<bndbox>
			<xmin>357</xmin>
			<ymin>371</ymin>
			<xmax>406</xmax>
			<ymax>457</ymax>
		</bndbox>
	</object>
	<object>
		<name>ecocup</name>
		<pose>Unspecified</pose>
		<truncated>0</truncated>
		<difficult>0</difficult>
		<bndbox>
			<xmin>444</xmin>
			<ymin>396</ymin>
			<xmax>492</xmax>
			<ymax>493</ymax>
		</bndbox>
	</object>
	<object>
		<name>ecocup</name>
		<pose>Unspecified</pose>
		<truncated>0</truncated>
		<difficult>1</difficult>
		<bndbox>
			<xmin>551</xmin>
			<ymin>405</ymin>
			<xmax>596</xmax>
			<ymax>492</ymax>
		</bndbox>
	</object>
</annotation>
