<annotation>
	<folder>annotation_images_eco_cup</folder>
	<filename>hoxuanvi_pos_009.jpg</filename>
	<path>hoxuanvi_pos_009.jpg</path>
	<source>
		<database>Unknown</database>
	</source>
	<size>
		<width>2992</width>
		<height>4000</height>
		<depth>3</depth>
	</size>
	<segmented>0</segmented>
	<object>
		<name>ecocup</name>
		<pose>Unspecified</pose>
		<truncated>0</truncated>
		<difficult>0</difficult>
		<bndbox>
			<xmin>643</xmin>
			<ymin>712</ymin>
			<xmax>2101</xmax>
			<ymax>3036</ymax>
		</bndbox>
	</object>
</annotation>
