<annotation>
	<folder>lelongph</folder>
	<filename>jchabbal_pos_004.jpg</filename>
	<path>jchabbal_pos_004.jpg</path>
	<source>
		<database>Unknown</database>
	</source>
	<size>
		<width>1154</width>
		<height>866</height>
		<depth>3</depth>
	</size>
	<segmented>0</segmented>
	<object>
		<name>ecocup</name>
		<pose>Unspecified</pose>
		<truncated>1</truncated>
		<difficult>0</difficult>
		<bndbox>
			<xmin>164</xmin>
			<ymin>349</ymin>
			<xmax>449</xmax>
			<ymax>866</ymax>
		</bndbox>
	</object>
	<object>
		<name>ecocup</name>
		<pose>Unspecified</pose>
		<truncated>0</truncated>
		<difficult>1</difficult>
		<bndbox>
			<xmin>649</xmin>
			<ymin>418</ymin>
			<xmax>862</xmax>
			<ymax>779</ymax>
		</bndbox>
	</object>
</annotation>
