<annotation>
	<folder>bmissaou</folder>
	<filename>mparache_pos_009.jpg</filename>
	<path>mparache_pos_009.jpg</path>
	<source>
		<database>Unknown</database>
	</source>
	<size>
		<width>3456</width>
		<height>4608</height>
		<depth>3</depth>
	</size>
	<segmented>0</segmented>
	<object>
		<name>ecocup</name>
		<pose>Unspecified</pose>
		<truncated>0</truncated>
		<difficult>1</difficult>
		<bndbox>
			<xmin>610</xmin>
			<ymin>1556</ymin>
			<xmax>1527</xmax>
			<ymax>3662</ymax>
		</bndbox>
	</object>
	<object>
		<name>ecocup</name>
		<pose>Unspecified</pose>
		<truncated>0</truncated>
		<difficult>0</difficult>
		<bndbox>
			<xmin>1460</xmin>
			<ymin>1889</ymin>
			<xmax>2677</xmax>
			<ymax>2862</ymax>
		</bndbox>
	</object>
</annotation>
